beret_utils/__init__.py
beret_utils/bereTools.py
beret_utils/config.py
beret_utils/cpimap.py
beret_utils/djangoTools.py
beret_utils/global_request.py
beret_utils/imap.py
beret_utils/mapping.py
beret_utils/path_data.py
beret_utils/path_generator.py
beret_utils/patterns.py
beret_utils/random_code.py
beret_utils/singleton.py
beret_utils/svn_diff.py
beret_utils/tail_recursion.py
beret_utils/trace.py
beret_utils/wait_for_postgresql.py
example/__init__.py
example/config.py
beret_utils-0.4.9.dist-info/LICENSE
beret_utils-0.4.9.dist-info/METADATA
beret_utils-0.4.9.dist-info/WHEEL
beret_utils-0.4.9.dist-info/top_level.txt
beret_utils-0.4.9.dist-info/RECORD
