Metadata-Version: 2.1
Name: beret_utils
Version: 0.4.9
Summary: Subjective Python tools selection.
Home-page: https://github.com/berecik/python_utils
Author: Adam Beret Manczuk
Author-email: beret@hipisi.org.pl
License: MIT
Classifier: License :: OSI Approved :: MIT License
Classifier: Programming Language :: Python
Classifier: Programming Language :: Python :: 3
Classifier: Programming Language :: Python :: 3.9
Classifier: Programming Language :: Python :: Implementation :: CPython
Classifier: Programming Language :: Python :: Implementation :: PyPy
Requires-Python: >=3.9.0
License-File: LICENSE
